db/__init__.py
db/base_database.py
db/base_doc.py
db/base_model.py
db/base_query_filter.py
db/base_query_params.py
db/base_query_search.py
db/beanie_database.py
db/exception.py
db/paginated_model.py
db/sqlite_database.py
db/repository/__init__.py
db/repository/abstract_repository.py
db/repository/beanie_repository.py
db/repository/sqlalchemy_repository.py
ildev_db-0.0.14.dist-info/METADATA
ildev_db-0.0.14.dist-info/WHEEL
ildev_db-0.0.14.dist-info/top_level.txt
ildev_db-0.0.14.dist-info/RECORD
