Metadata-Version: 2.4
Name: ildev-db
Version: 0.0.14
Summary: Reusable SQLite + SQLAlchemy and MongoDB + Beanie async repository module
Author: Ilias Aiupov
Classifier: Programming Language :: Python :: 3.9
Classifier: Programming Language :: Python :: 3.10
Classifier: Programming Language :: Python :: 3.11
Classifier: License :: OSI Approved :: MIT License
Classifier: Operating System :: OS Independent
Requires-Python: >=3.8
Requires-Dist: sqlalchemy[asyncio]
Requires-Dist: aiosqlite
Requires-Dist: beanie
Requires-Dist: motor
Requires-Dist: pydantic
Requires-Dist: ildev-log>=0.0.3
Provides-Extra: build
Requires-Dist: build; extra == "build"
Requires-Dist: twine; extra == "build"
Provides-Extra: test
Requires-Dist: pytest; extra == "test"
Requires-Dist: pytest-asyncio; extra == "test"
Provides-Extra: dev
Requires-Dist: build; extra == "dev"
Requires-Dist: twine; extra == "dev"
Requires-Dist: pytest; extra == "dev"
Requires-Dist: pytest-asyncio; extra == "dev"
